{"date": "1980-10-21", "details": [
{"detail_idx": 0, "officer_id": "Q5607249", "continues": [], "relinquishes": [], "assumes": [["Ministry of Education", "Cabinet Minister"]]},
{"detail_idx": 1, "officer_id": "Q7238171", "continues": [], "relinquishes": [["Ministry of Works and Housing", "Cabinet Minister"]], "assumes": [["Ministry of Petroleum Chemicals and Fertilisers", "Cabinet Minister"]]},
{"detail_idx": 2, "officer_id": "Q7918212", "continues": [], "relinquishes": [["Ministry of Petroleum Chemicals and Fertilisers", "Cabinet Minister"]], "assumes": [["Ministry of Shipping and Transport", "Cabinet Minister"]]},
{"detail_idx": 3, "officer_id": "Q4901829", "continues": [], "relinquishes": [["Ministry of Parliamentary Affairs", "Cabinet Minister"], ["Ministry of Labour", "Cabinet Minister"]], "assumes": [["Ministry of Parliamentary Affairs", "Cabinet Minister"], ["Ministry of Works and Housing", "Cabinet Minister"]]},
{"detail_idx": 4, "officer_id": "Q3520007", "continues": [], "relinquishes": [["Ministry of Planning", "Cabinet Minister"]], "assumes": [["Ministry of Planning", "Cabinet Minister"], ["Ministry of Labour", "Cabinet Minister"]]},
{"detail_idx": 5, "officer_id": "Q16012160", "continues": [], "relinquishes": [["Ministry of Shipping and Transport", "Cabinet Minister"], ["Ministry of Civil Aviation and Tourism", "Cabinet Minister"]], "assumes": [["Ministry of Civil Aviation and Tourism", "Cabinet Minister"]]},
{"detail_idx": 6, "officer_id": "Q7916339", "continues": [], "relinquishes": [["Ministry of Information and Broadcasting", "Cabinet Minister"], ["Ministry of Supply", "Cabinet Minister"]], "assumes": [["Ministry of Information and Broadcasting", "Cabinet Minister"]]},
{"detail_idx": 7, "officer_id": "Q4834211", "continues": [], "relinquishes": [["Ministry of Education", "Cabinet Minister"], ["Ministry of Health", "Cabinet Minister"], ["Ministry of Welfare", "Cabinet Minister"]], "assumes": [["Ministry of Health and Family Welfare", "Cabinet Minister"]]},
{"detail_idx": 8, "officer_id": "Q4900694", "continues": [], "relinquishes": [], "assumes": [["Ministry of Supply", "Minister of State (Independent Charge)"]]},
{"detail_idx": 9, "officer_id": "Q6403123", "continues": [], "relinquishes": [], "assumes": [["Ministry of Commerce", "Minister of State"]]},
{"detail_idx": 10, "officer_id": "Q7493078", "continues": [], "relinquishes": [], "assumes": [["Ministry of Education", "Minister of State"]]},
{"detail_idx": 11, "officer_id": "Q51092734", "continues": [], "relinquishes": [], "assumes": [["Ministry of Finance", "Minister of State"]]},
{"detail_idx": 12, "officer_id": "Q1897174", "continues": [], "relinquishes": [], "assumes": [["Ministry of Defence", "Minister of State"]]},
{"detail_idx": 13, "officer_id": "Q62566732", "continues": [], "relinquishes": [], "assumes": [["Ministry of Agriculture", "Minister of State"]]},
{"detail_idx": 14, "officer_id": "Q94652215", "continues": [], "relinquishes": [["Ministry of Commerce", "Minister of State"]], "assumes": [["Ministry of Irrigation", "Minister of State"]]},
{"detail_idx": 15, "officer_id": "Q5071023", "continues": [], "relinquishes": [["Ministry of Defence", "Minister of State"]], "assumes": [["Department of Science and Technology", "Minister of State"]]},
{"detail_idx": 16, "officer_id": "Q6323911", "continues": [], "relinquishes": [["Ministry of Information and Broadcasting", "Minister of State"]], "assumes": [["Ministry of Labour", "Minister of State"]]},
{"detail_idx": 17, "officer_id": "Q61717528", "continues": [], "relinquishes": [], "assumes": [["Ministry of Civil Supplies", "Deputy Minister"]]},
{"detail_idx": 18, "officer_id": "Q6444064", "continues": [], "relinquishes": [], "assumes": [["Ministry of Information and Broadcasting", "Deputy Minister"]]},
{"detail_idx": 19, "officer_id": "Q42308999", "continues": [], "relinquishes": [], "assumes": [["Ministry of Agriculture", "Deputy Minister"]]},
{"detail_idx": 20, "officer_id": "Q45334923", "continues": [], "relinquishes": [["Department of Science and Technology", "Deputy Minister"]], "assumes": [["Ministry of Communications", "Deputy Minister"]]},
{"detail_idx": 21, "officer_id": "Q110322103", "continues": [], "relinquishes": [["Ministry of Industry", "Deputy Minister"]], "assumes": [["Ministry of Labour", "Deputy Minister"]]}
]}