{"date": "1993-02-19", "details": [
{"detail_idx": 0, "officer_id": "Q1897029", "continues": [["Ministry of Personnel Public Grievances and Pensions", "Minister of State"]], "relinquishes": [], "assumes": [["Ministry of Parliamentary Affairs", "Minister of State"]]},
{"detail_idx": 1, "officer_id": "Q6933652", "continues": [["Ministry of Human Resource Development", "Minister of State"]], "relinquishes": [], "assumes": [["Ministry of Parliamentary Affairs", "Minister of State"]]},
{"detail_idx": 2, "officer_id": "Q7240137", "continues": [["Ministry of Urban Development", "Minister of State"]], "relinquishes": [], "assumes": [["Ministry of Drinking Water and Sanitation", "Minister of State"]]},
{"detail_idx": 3, "officer_id": "Q46992870", "continues": [["Ministry of New and Renewable Energy", "Minister of State"]], "relinquishes": [], "assumes": [["Ministry of Agriculture", "Minister of State"]]},
{"detail_idx": 4, "officer_id": "Q13116273", "continues": [["Ministry of Civil Supplies", "Minister of State"], ["Ministry of Consumer Affairs, Food and Public Distribution", "Minister of State"]], "relinquishes": [], "assumes": [["Ministry of Commerce", "Minister of State"]]},
{"detail_idx": 5, "officer_id": "Q6437486", "continues": [["Ministry of Industry", "Minister of State"]], "relinquishes": [], "assumes": [["Ministry of Industry", "Minister of State"]]}
]}